beorn/__init__.py
beorn/astro.py
beorn/bias.py
beorn/cloud_in_cell.py
beorn/compute_profiles.py
beorn/computing_profiles.py
beorn/constants.py
beorn/cosmo.py
beorn/couplings.py
beorn/cross_sections.py
beorn/excursion_set.py
beorn/functions.py
beorn/global_qty.py
beorn/gravity.py
beorn/halo_finder.py
beorn/halomassfunction.py
beorn/halomodel_on_grid.py
beorn/lightcones.py
beorn/luminosity_function.py
beorn/massaccretion.py
beorn/nbody_interface.py
beorn/param.py
beorn/plotting.py
beorn/profiles_on_grid.py
beorn/run.py
beorn/trash.py
beorn/files/PCDM_Planck.dat
beorn/files/corr_fct.dat
beorn/input_data/kappa_HH.dat
beorn/input_data/kappa_eH.dat
beorn/input_data/recfrac.dat
beorn-0.0.1.dist-info/LICENSE
beorn-0.0.1.dist-info/METADATA
beorn-0.0.1.dist-info/WHEEL
beorn-0.0.1.dist-info/top_level.txt
beorn-0.0.1.dist-info/RECORD
