Metadata-Version: 2.1
Name: beorn
Version: 0.0.1
Author: T.Schaeffer, S.Giri, A.Schneider
Author-email: sambit.giri@su.se
License-File: LICENSE
Requires-Dist: numpy
Requires-Dist: scipy
Requires-Dist: matplotlib
Requires-Dist: pytest
Requires-Dist: tools21cm
